audioinfo/__init__.py
audioinfo/__main__.py
audioinfo/main.py
audioinfo_ecrit-0.1.3.dist-info/METADATA
audioinfo_ecrit-0.1.3.dist-info/WHEEL
audioinfo_ecrit-0.1.3.dist-info/entry_points.txt
audioinfo_ecrit-0.1.3.dist-info/top_level.txt
audioinfo_ecrit-0.1.3.dist-info/RECORD
